pycurl2
