Metadata-Version: 1.1
Name: pycurl2
Version: 7.20.0
Summary: PycURL2 - cURL library module for python
Home-page: http://pycurl2.github.com
Author: Alexandr Lispython (2012), Kjetil Jacobsen (2001 - 2008), Markus F.X.J. Oberhumer (2001 - 2008)
Author-email: alex@obout.ru [kjetilja at gmail.com, markus at oberhumer.com]
License: LGPL/MIT
Keywords: curl,pycurl,http library
Platform: Linux
Platform: Mac
Platform: Windows
Classifier: Development Status :: 5 - Production/Stable
Classifier: Environment :: Web Environment
Classifier: Intended Audience :: Developers
Classifier: License :: OSI Approved :: GNU Library or Lesser General Public License (LGPL)
Classifier: Operating System :: Microsoft :: Windows
Classifier: Operating System :: POSIX
Classifier: Programming Language :: Python
Classifier: Topic :: Internet :: WWW/HTTP
Classifier: Programming Language :: Python :: 2.5
Classifier: Programming Language :: Python :: 2.6
Classifier: Programming Language :: Python :: 2.7
